pytenet/__init__.py
pytenet/bipartite_graph.py
pytenet/bond_ops.py
pytenet/evolution.py
pytenet/hamiltonian.py
pytenet/krylov.py
pytenet/minimization.py
pytenet/mpo.py
pytenet/mps.py
pytenet/opchain.py
pytenet/operation.py
pytenet/opgraph.py
pytenet/optree.py
pytenet/qnumber.py
pytenet/util.py
pytenet-1.2.0.dist-info/LICENSE
pytenet-1.2.0.dist-info/METADATA
pytenet-1.2.0.dist-info/WHEEL
pytenet-1.2.0.dist-info/top_level.txt
pytenet-1.2.0.dist-info/RECORD
