Metadata-Version: 2.1
Name: pytenet
Version: 1.2.0
Summary: Tensor network library for quantum simulations
Home-page: https://github.com/cmendl/pytenet
Author: Christian B. Mendl
Author-email: "Christian B. Mendl" <christian.b.mendl@gmail.com>
License: BSD-2-Clause
Project-URL: Homepage, https://github.com/cmendl/pytenet
Requires-Python: >=3.6
License-File: LICENSE
Requires-Dist: numpy
Requires-Dist: scipy
Provides-Extra: test
Requires-Dist: unittest ; extra == 'test'
